uselessutilities/__init__.py
uselessutilities/__main__.py
uselessutilities/cli.py
uselessutilities/nonary.py
uselessutilities/quaternary.py
uselessutilities/quinary.py
uselessutilities/senary.py
uselessutilities/septenary.py
uselessutilities/ternary.py
uselessutilities-1.1.5.dist-info/licenses/LICENSE
uselessutilities-1.1.5.dist-info/METADATA
uselessutilities-1.1.5.dist-info/WHEEL
uselessutilities-1.1.5.dist-info/top_level.txt
uselessutilities-1.1.5.dist-info/RECORD
