Metadata-Version: 2.4
Name: uselessutilities
Version: 1.1.5
Summary: Convert integers to obscure bases
Author-email: Creatorlibs <creatorlibs@protonmail.com>
License: MIT
License-File: LICENSE
Dynamic: license-file
